daxparser/DAXLexer.g4
daxparser/DAXLexer.interp
daxparser/DAXLexer.py
daxparser/DAXLexer.tokens
daxparser/__init__.py
daxparser/api.py
daxparser-0.1.3.dist-info/METADATA
daxparser-0.1.3.dist-info/WHEEL
daxparser-0.1.3.dist-info/RECORD
