Metadata-Version: 2.1
Name: daxparser
Version: 0.1.3
Summary: 
Author: Adrian Ehrsam
Author-email: myemailiscensored@bmsuisse.ch
Requires-Python: >=3.9,<4.0
Classifier: Programming Language :: Python :: 3
Classifier: Programming Language :: Python :: 3.9
Classifier: Programming Language :: Python :: 3.10
Classifier: Programming Language :: Python :: 3.11
Classifier: Programming Language :: Python :: 3.12
Requires-Dist: antlr4-python3-runtime (>=4.13.0,<5.0.0)
Requires-Dist: requests (>=2.31.0,<3.0.0)
